yao/__init__.py
yao/crud.py
yao/db.py
yao/depends.py
yao/helpers.py
yao/method.py
yao/schema.py
yao/function/__init__.py
yao/function/main.py
yao/function/model.py
yao/function/annex/__init__.py
yao/function/annex/crud.py
yao/function/annex/main.py
yao/function/annex/schema.py
yao/function/appointment/__init__.py
yao/function/appointment/crud.py
yao/function/appointment/main.py
yao/function/appointment/schema.py
yao/function/company/__init__.py
yao/function/company/crud.py
yao/function/company/main.py
yao/function/company/schema.py
yao/function/department/__init__.py
yao/function/department/crud.py
yao/function/department/main.py
yao/function/department/schema.py
yao/function/log/__init__.py
yao/function/log/crud.py
yao/function/log/main.py
yao/function/log/schema.py
yao/function/permission/__init__.py
yao/function/permission/crud.py
yao/function/permission/main.py
yao/function/permission/schema.py
yao/function/queue/__init__.py
yao/function/queue/crud.py
yao/function/queue/helper.py
yao/function/queue/main.py
yao/function/queue/schema.py
yao/function/queue/type.py
yao/function/user/__init__.py
yao/function/user/crud.py
yao/function/user/main.py
yao/function/user/schema.py
yao/wxamp/__init__.py
yao/wxamp/base.py
yao/wxmp/__init__.py
yao/wxmp/base.py
yao-0.1.5.dist-info/METADATA
yao-0.1.5.dist-info/WHEEL
yao-0.1.5.dist-info/top_level.txt
yao-0.1.5.dist-info/RECORD
